[
  {"version":1},
  {"ingredient":{"id":"occultism:otherrock"},"type":"item_stack","bookmarkType":"INGREDIENT"},
  {"ingredient":{"id":"occultism:ritual_dummy/summon_djinni_gambler"},"type":"item_stack","bookmarkType":"INGREDIENT"},
  {"ingredient":{"id":"occultism:spawn_egg/foliot","components":{"minecraft:item_name":"{\"translate\":\"item.occultism.ritual_dummy.summon_foliot_otherrock_trader\"}","minecraft:lore":["{\"translate\":\"item.occultism.ritual_dummy.summon_foliot_otherrock_trader.tooltip\"}"]}},"type":"item_stack","bookmarkType":"INGREDIENT"},
  {"ingredient":{"id":"occultism:ritual_dummy/summon_foliot_otherrock_trader"},"type":"item_stack","bookmarkType":"INGREDIENT"},
  {"ingredient":{"id":"occultism:spawn_egg/foliot","components":{"minecraft:item_name":"{\"translate\":\"item.occultism.ritual_dummy.summon_foliot_crystallizer\"}","minecraft:lore":["{\"translate\":\"item.occultism.ritual_dummy.summon_foliot_crystallizer.tooltip\"}"]}},"type":"item_stack","bookmarkType":"INGREDIENT"},
  {"ingredient":{"id":"minecraft:stick"},"type":"item_stack","bookmarkType":"INGREDIENT"},
  {"ingredient":{"id":"occultism:otherstone"},"type":"item_stack","bookmarkType":"INGREDIENT"},
  {"ingredient":{"id":"minecraft:oak_log"},"type":"item_stack","bookmarkType":"INGREDIENT"},
  {"ingredient":{"id":"occultism:ritual_dummy/summon_foliot_otherstone_trader"},"type":"item_stack","bookmarkType":"INGREDIENT"},
  {"ingredient":{"id":"occultism:spawn_egg/wondering_trader"},"type":"item_stack","bookmarkType":"INGREDIENT"},
  {"ingredient":{"id":"occultism:dimensional_mineshaft"},"type":"item_stack","bookmarkType":"INGREDIENT"},
  {"ingredient":{"id":"occultism:otherstone_tablet"},"type":"item_stack","bookmarkType":"INGREDIENT"},
  {"ingredient":{"id":"occultism:infused_lenses"},"type":"item_stack","bookmarkType":"INGREDIENT"},
  {"ingredient":{"id":"occultism:lens_frame"},"type":"item_stack","bookmarkType":"INGREDIENT"},
  {"ingredient":{"id":"occultism:entity_wormhole_dark"},"type":"item_stack","bookmarkType":"INGREDIENT"},
  {"ingredient":{"id":"occultism:iesnium_ingot"},"type":"item_stack","bookmarkType":"INGREDIENT"},
  {"ingredient":{"id":"minecraft:reinforced_deepslate"},"type":"item_stack","bookmarkType":"INGREDIENT"},
  {"ingredient":{"id":"occultism:sacrificial_bowl"},"type":"item_stack","bookmarkType":"INGREDIENT"},
  {"ingredient":{"id":"occultism:dark_sacrificial_bowl"},"type":"item_stack","bookmarkType":"INGREDIENT"},
  {"ingredient":{"id":"occultism:burnt_otherstone"},"type":"item_stack","bookmarkType":"INGREDIENT"},
  {"ingredient":{"id":"occultism:awakened_feather"},"type":"item_stack","bookmarkType":"INGREDIENT"},
  {"ingredient":{"id":"occultism:iesnium_ore"},"type":"item_stack","bookmarkType":"INGREDIENT"},
  {"ingredient":{"id":"occultism:raw_iesnium"},"type":"item_stack","bookmarkType":"INGREDIENT"},
  {"ingredient":{"id":"occultism:demons_dream_essence"},"type":"item_stack","bookmarkType":"INGREDIENT"},
  {"ingredient":{"id":"occultism:otherworld_essence"},"type":"item_stack","bookmarkType":"INGREDIENT"},
  {"ingredient":{"id":"minecraft:lingering_potion","components":{"minecraft:potion_contents":{"potion":"occultism:third_eye_potion"}}},"type":"item_stack","bookmarkType":"INGREDIENT"},
  {"ingredient":{"id":"minecraft:tipped_arrow","components":{"minecraft:potion_contents":{"potion":"occultism:third_eye_potion"}}},"type":"item_stack","bookmarkType":"INGREDIENT"},
  {"ingredient":{"id":"occultism:gray_paste"},"type":"item_stack","bookmarkType":"INGREDIENT"},
  {"ingredient":{"id":"minecraft:redstone"},"type":"item_stack","bookmarkType":"INGREDIENT"},
  {"ingredient":{"id":"occultism:burnt_otherrock"},"type":"item_stack","bookmarkType":"INGREDIENT"},
  {"ingredient":{"id":"occultism:otherrock_frame"},"type":"item_stack","bookmarkType":"INGREDIENT"},
  {"ingredient":{"id":"occultism:otherflower"},"type":"item_stack","bookmarkType":"INGREDIENT"},
  {"ingredient":{"id":"divinerpg:bedrock_chunk"},"type":"item_stack","bookmarkType":"INGREDIENT"},
  {"ingredient":{"id":"divinerpg:bedrock_sword"},"type":"item_stack","bookmarkType":"INGREDIENT"},
  {"ingredient":{"id":"minecraft:bedrock"},"type":"item_stack","bookmarkType":"INGREDIENT"},
  {"ingredient":{"id":"occultism:dictionary_of_spirits","components":{"modonomicon:book_id":"occultism:dictionary_of_spirits","modonomicon:book_open":false}},"type":"item_stack","bookmarkType":"INGREDIENT"},
  {"ingredient":{"id":"occultism:book_of_binding_foliot"},"type":"item_stack","bookmarkType":"INGREDIENT"},
  {"ingredient":{"id":"occultism:book_of_binding_bound_foliot"},"type":"item_stack","bookmarkType":"INGREDIENT"},
  {"ingredient":{"id":"occultism:ritual_dummy/summon_wondering_trader"},"type":"item_stack","bookmarkType":"INGREDIENT"},
  {"ingredient":{"id":"occultism:flame_of_automation"},"type":"item_stack","bookmarkType":"INGREDIENT"},
  {"ingredient":{"id":"occultism:crushed_end_stone"},"type":"item_stack","bookmarkType":"INGREDIENT"},
  {"ingredient":{"id":"occultism:otherglass_natural"},"type":"item_stack","bookmarkType":"INGREDIENT"},
  {"ingredient":{"id":"occultism:otherrock_natural"},"type":"item_stack","bookmarkType":"INGREDIENT"},
  {"ingredient":{"id":"occultism:otherstone_natural"},"type":"item_stack","bookmarkType":"INGREDIENT"},
  {"ingredient":{"id":"minecraft:candle"},"type":"item_stack","bookmarkType":"INGREDIENT"},
  {"ingredient":{"id":"minecraft:porkchop"},"type":"item_stack","bookmarkType":"INGREDIENT"},
  {"ingredient":{"id":"occultism:tallow"},"type":"item_stack","bookmarkType":"INGREDIENT"},
  {"ingredient":{"id":"occultism:large_candle"},"type":"item_stack","bookmarkType":"INGREDIENT"},
  {"ingredient":{"id":"occultism:large_candle_brown"},"type":"item_stack","bookmarkType":"INGREDIENT"},
  {"ingredient":{"id":"occultism:large_candle_white"},"type":"item_stack","bookmarkType":"INGREDIENT"},
  {"ingredient":{"id":"occultism:dragonyst_dust"},"type":"item_stack","bookmarkType":"INGREDIENT"},
  {"ingredient":{"id":"occultism:echo_dust"},"type":"item_stack","bookmarkType":"INGREDIENT"},
  {"ingredient":{"id":"occultism:otherplanks"},"type":"item_stack","bookmarkType":"INGREDIENT"},
  {"ingredient":{"id":"create:millstone"},"type":"item_stack","bookmarkType":"INGREDIENT"},
  {"ingredient":{"id":"create:wrench"},"type":"item_stack","bookmarkType":"INGREDIENT"},
  {"ingredient":{"id":"create:andesite_alloy"},"type":"item_stack","bookmarkType":"INGREDIENT"},
  {"ingredient":{"id":"create:andesite_casing"},"type":"item_stack","bookmarkType":"INGREDIENT"},
  {"ingredient":{"id":"create:clutch"},"type":"item_stack","bookmarkType":"INGREDIENT"},
  {"ingredient":{"id":"occultism:iesnium_dust"},"type":"item_stack","bookmarkType":"INGREDIENT"},
  {"ingredient":{"id":"minecraft:apple"},"type":"item_stack","bookmarkType":"INGREDIENT"},
  {"ingredient":{"id":"minecraft:obsidian"},"type":"item_stack","bookmarkType":"INGREDIENT"},
  {"ingredient":{"id":"minecraft:flint_and_steel","components":{"minecraft:damage":11}},"type":"item_stack","bookmarkType":"INGREDIENT"},
  {"ingredient":{"id":"kubejs:fire_making_equipment"},"type":"item_stack","bookmarkType":"INGREDIENT"},
  {"ingredient":{"id":"minecraft:diamond_hoe"},"type":"item_stack","bookmarkType":"INGREDIENT"},
  {"ingredient":{"id":"immersiveengineering:seed"},"type":"item_stack","bookmarkType":"INGREDIENT"},
  {"ingredient":{"id":"occultism:datura_seeds"},"type":"item_stack","bookmarkType":"INGREDIENT"},
  {"ingredient":{"id":"minecraft:short_grass"},"type":"item_stack","bookmarkType":"INGREDIENT"},
  {"ingredient":{"id":"occultism:spirit_fire"},"type":"item_stack","bookmarkType":"INGREDIENT"},
  {"ingredient":{"id":"minecraft:calcite"},"type":"item_stack","bookmarkType":"INGREDIENT"},
  {"ingredient":{"id":"occultism:crushed_calcite"},"type":"item_stack","bookmarkType":"INGREDIENT"},
  {"ingredient":{"id":"occultism:otherstone_pedestal"},"type":"item_stack","bookmarkType":"INGREDIENT"},
  {"ingredient":{"id":"occultism:chalk_void"},"type":"item_stack","bookmarkType":"INGREDIENT"},
  {"ingredient":{"id":"occultism:chalk_rainbow"},"type":"item_stack","bookmarkType":"INGREDIENT"},
  {"ingredient":{"id":"occultism:golden_sacrificial_bowl"},"type":"item_stack","bookmarkType":"INGREDIENT"},
  {"ingredient":{"id":"occultism:ritual_dummy/craft_iesnium_sacrificial_bowl"},"type":"item_stack","bookmarkType":"INGREDIENT"},
  {"ingredient":{"id":"modern_industrialization:steel_dust"},"type":"item_stack","bookmarkType":"INGREDIENT"},
  {"ingredient":{"id":"modern_industrialization:steel_ingot"},"type":"item_stack","bookmarkType":"INGREDIENT"},
  {"ingredient":{"id":"immersiveengineering:drillhead_steel"},"type":"item_stack","bookmarkType":"INGREDIENT"},
  {"ingredient":{"id":"minecraft:chest"},"type":"item_stack","bookmarkType":"INGREDIENT"},
  {"ingredient":{"id":"actuallyadditions:phantom_itemface"},"type":"item_stack","bookmarkType":"INGREDIENT"},
  {"ingredient":{"id":"actuallyadditions:phantom_placer"},"type":"item_stack","bookmarkType":"INGREDIENT"},
  {"ingredient":{"id":"actuallyadditions:ender_star"},"type":"item_stack","bookmarkType":"INGREDIENT"},
  {"ingredient":{"id":"actuallyadditions:wings_of_the_bats"},"type":"item_stack","bookmarkType":"INGREDIENT"},
  {"ingredient":{"id":"occultism:divination_rod","components":{"occultism:divination_linked_block":"occultism:otherworld_log_natural","occultism:divination_distance":7.0,"occultism:divination_pos":[2118,32,-2533]}},"type":"item_stack","bookmarkType":"INGREDIENT"},
  {"ingredient":{"id":"occultism:spirit_attuned_gem"},"type":"item_stack","bookmarkType":"INGREDIENT"},
  {"ingredient":{"id":"modern_industrialization:diamond_dust"},"type":"item_stack","bookmarkType":"INGREDIENT"},
  {"ingredient":{"id":"modern_industrialization:steel_plate"},"type":"item_stack","bookmarkType":"INGREDIENT"},
  {"ingredient":{"id":"minecraft:shield"},"type":"item_stack","bookmarkType":"INGREDIENT"},
  {"ingredient":{"id":"ironchest:diamond_chest"},"type":"item_stack","bookmarkType":"INGREDIENT"},
  {"ingredient":{"id":"ironchest:iron_chest"},"type":"item_stack","bookmarkType":"INGREDIENT"},
  {"ingredient":{"id":"ironchest:copper_chest"},"type":"item_stack","bookmarkType":"INGREDIENT"},
  {"ingredient":{"id":"ironchest:crystal_chest"},"type":"item_stack","bookmarkType":"INGREDIENT"},
  {"ingredient":{"id":"ironchest:trapped_crystal_chest"},"type":"item_stack","bookmarkType":"INGREDIENT"},
  {"ingredient":{"id":"ironchest:obsidian_chest"},"type":"item_stack","bookmarkType":"INGREDIENT"},
  {"ingredient":{"id":"ironchest:gold_chest"},"type":"item_stack","bookmarkType":"INGREDIENT"},
  {"ingredient":{"id":"ironchest:dirt_chest"},"type":"item_stack","bookmarkType":"INGREDIENT"},
  {"ingredient":{"id":"sophisticatedbackpacks:backpack"},"type":"item_stack","bookmarkType":"INGREDIENT"},
  {"ingredient":{"id":"minecraft:string"},"type":"item_stack","bookmarkType":"INGREDIENT"},
  {"ingredient":{"id":"sophisticatedbackpacks:backpack","components":{"sophisticatedcore:main_color":-425955,"sophisticatedcore:accent_color":-425955}},"type":"item_stack","bookmarkType":"INGREDIENT"},
  {"ingredient":{"id":"sophisticatedbackpacks:backpack","components":{"sophisticatedcore:number_of_inventory_slots":27,"sophisticatedcore:storage_uuid":[2140384168,849298792,-1724535237,1890861240],"sophisticatedcore:number_of_upgrade_slots":1,"sophisticatedcore:render_info_tag":{"upgradeItems":[{}]}}},"type":"item_stack","bookmarkType":"INGREDIENT"}
]